{
  "metadata": {
    "id": "review-producer-api-as-consumer",
    "name": "Review Producer API As Consumer",
    "shortDescription": "Review functional spec + OpenAPI from a consumer perspective and produce questions for producers plus early dev priorities.",
    "description": "For a demand folder, select the latest functional specification and OpenAPI contract, perform a consumer-driven review to identify unclear behaviors, integration risks, and contract gaps, and produce a structured review document with questions for the producer team.",
    "objectives": [
      "Select latest functional spec and OpenAPI artifacts for a demand",
      "Identify consumer-facing questions and ambiguities blocking implementation",
      "Identify early development priorities and high-risk integration areas",
      "Produce a structured consumer review under docs/specifications/{demand_folder}/09-consumer-review"
    ],
    "tags": [
      "api",
      "openapi",
      "consumer",
      "spec-review",
      "questions",
      "integration"
    ],
    "status": "experimental",
    "exposure": "internal",
    "version": "1.0.0",
    "protocol": "Propose-Confirm-Act",
    "aliases": [
      "review api as consumer",
      "consumer api review",
      "review producer openapi",
      "consumer perspective review"
    ],
    "author": "OLAF Framework",
    "created": "2025-12-15",
    "updated": "2026-01-14"
  },
  "bom": {
    "prompts": [
      {
        "name": "review-producer-api-as-consumer",
        "path": "/skill.md",
        "description": "Main workflow entry point"
      }
    ],
    "templates": [
      {
        "name": "consumer-review-report-template",
        "path": "templates/consumer-review-report-template.md",
        "type": "markdown"
      }
    ],
    "docs": [
      {
        "name": "description",
        "path": "/docs/description.md",
        "type": "description"
      },
      {
        "name": "tutorial",
        "path": "/docs/tutorial.md",
        "type": "tutorial"
      }
    ]
  }
}